LICENCE.txt
README.md
setup.py
src/Gen/__init__.py
src/Gen/utils.py
src/GenUserAgent.egg-info/PKG-INFO
src/GenUserAgent.egg-info/SOURCES.txt
src/GenUserAgent.egg-info/dependency_links.txt
src/GenUserAgent.egg-info/top_level.txt