Metadata-Version: 2.1
Name: GenUserAgent
Version: 1.8
Summary: Thư Viện Hỗ Trợ Tạo UserAgent, Console v.v
Home-page: 
Author: lam
Author-email: ldl.contact.booking@gmail.com
Classifier: Development Status :: 5 - Production/Stable
Classifier: Intended Audience :: Education
Classifier: Operating System :: Microsoft :: Windows :: Windows 10
Classifier: License :: OSI Approved :: MIT License
Classifier: Programming Language :: Python :: 3
Requires-Python: >=3.6
License-File: LICENCE.txt
